{
  "id": "ev-mqrcnoz3-9a26d3",
  "objectiveRunId": "run-mqrcnoyq-54d4c9",
  "sourceType": "reflection",
  "sourceRef": "executive-reflection",
  "summary": "Confidence: 40% (low) | Assumptions: 2 | Missing: 1",
  "sha256": "6911b5bc5ee5c4c354d6c4d8044e51a255b2628f17f939e2044cde7093b7345b",
  "artifactPath": "E:\\Project\\Master\\mi-core\\data\\evidence\\run-mqrcnoyq-54d4c9\\6911b5bc5ee5c4c354d6c4d8044e51a255b2628f17f939e2044cde7093b7345b.json",
  "capturedAt": "2026-06-24T00:43:18.447Z",
  "readOnly": true
}