{
  "coord_task_id": "OSS-172d01b500",
  "task_name": "Advance Prometheus past DISCOVERY",
  "objective_id": "OBJ-OSS-GOVERNANCE",
  "target": "oss_registry",
  "approval_level": "READ_ONLY",
  "operator_type": "oss_governance",
  "state": "CREATED",
  "created_at": 1782452013.7034926,
  "created_iso": "2026-06-26T05:33:33.703494+00:00",
  "updated_at": 1782452013.7035012,
  "owner": "it_lead",
  "priority": "MEDIUM",
  "description": "Prometheus has been in DISCOVERY \u2014 advance gate.",
  "source_signals": [
    {
      "project_id": "OSS-8b008b6ccc",
      "stage": "DISCOVERY",
      "days_in_stage": "unknown"
    }
  ],
  "evidence_ids": [],
  "state_history": [
    {
      "state": "CREATED",
      "timestamp": 1782452013.7035022
    }
  ]
}