{
  "id": "ev-mqrcnoy0-fa4349",
  "objectiveRunId": "run-mqrcnoxq-4c9e42",
  "sourceType": "reflection",
  "sourceRef": "executive-reflection",
  "summary": "Confidence: 40% (low) | Assumptions: 2 | Missing: 1",
  "sha256": "3ba6b1de0141868d2ad2a5b1ddb6453365db6772ea7eb00490c3ba0ff99cf872",
  "artifactPath": "E:\\Project\\Master\\mi-core\\data\\evidence\\run-mqrcnoxq-4c9e42\\3ba6b1de0141868d2ad2a5b1ddb6453365db6772ea7eb00490c3ba0ff99cf872.json",
  "capturedAt": "2026-06-24T00:43:18.408Z",
  "readOnly": true
}